{".class":"MypyFile","_fullname":"modules.chart_feedback.chart_feedback_modules","future_import_flags":[],"is_partial_stub_package":false,"is_stub":false,"names":{".class":"SymbolTable","MongoClient":{".class":"SymbolTableNode","kind":"Gdef","node":{".class":"Var","flags":["is_suppressed_import","is_ready","is_inferred"],"fullname":"modules.chart_feedback.chart_feedback_modules.MongoClient","name":"MongoClient","type":{".class":"AnyType","missing_import_name":"modules.chart_feedback.chart_feedback_modules.MongoClient","source_any":null,"type_of_any":3}}},"QdrantClient":{".class":"SymbolTableNode","kind":"Gdef","node":{".class":"Var","flags":["is_suppressed_import","is_ready","is_inferred"],"fullname":"modules.chart_feedback.chart_feedback_modules.QdrantClient","name":"QdrantClient","type":{".class":"AnyType","missing_import_name":"modules.chart_feedback.chart_feedback_modules.QdrantClient","source_any":null,"type_of_any":3}}},"__annotations__":{".class":"SymbolTableNode","kind":"Gdef","node":{".class":"Var","flags":["is_ready"],"fullname":"modules.chart_feedback.chart_feedback_modules.__annotations__","name":"__annotations__","type":{".class":"Instance","args":["builtins.str",{".class":"AnyType","missing_import_name":null,"source_any":null,"type_of_any":6}],"extra_attrs":null,"type_ref":"builtins.dict"}}},"__doc__":{".class":"SymbolTableNode","kind":"Gdef","node":{".class":"Var","flags":["is_ready"],"fullname":"modules.chart_feedback.chart_feedback_modules.__doc__","name":"__doc__","type":"builtins.str"}},"__file__":{".class":"SymbolTableNode","kind":"Gdef","node":{".class":"Var","flags":["is_ready"],"fullname":"modules.chart_feedback.chart_feedback_modules.__file__","name":"__file__","type":"builtins.str"}},"__name__":{".class":"SymbolTableNode","kind":"Gdef","node":{".class":"Var","flags":["is_ready"],"fullname":"modules.chart_feedback.chart_feedback_modules.__name__","name":"__name__","type":"builtins.str"}},"__package__":{".class":"SymbolTableNode","kind":"Gdef","node":{".class":"Var","flags":["is_ready"],"fullname":"modules.chart_feedback.chart_feedback_modules.__package__","name":"__package__","type":"builtins.str"}},"__spec__":{".class":"SymbolTableNode","kind":"Gdef","node":{".class":"Var","flags":["is_ready"],"fullname":"modules.chart_feedback.chart_feedback_modules.__spec__","name":"__spec__","type":"importlib.machinery.ModuleSpec"}},"collection_exists":{".class":"SymbolTableNode","kind":"Gdef","node":{".class":"FuncDef","abstract_status":0,"arg_kinds":[0,0],"arg_names":["db","collection_name"],"dataclass_transform_spec":null,"flags":[],"fullname":"modules.chart_feedback.chart_feedback_modules.collection_exists","name":"collection_exists","type":null}},"load_dotenv":{".class":"SymbolTableNode","kind":"Gdef","node":{".class":"Var","flags":["is_suppressed_import","is_ready","is_inferred"],"fullname":"modules.chart_feedback.chart_feedback_modules.load_dotenv","name":"load_dotenv","type":{".class":"AnyType","missing_import_name":"modules.chart_feedback.chart_feedback_modules.load_dotenv","source_any":null,"type_of_any":3}}},"os":{".class":"SymbolTableNode","cross_ref":"os","kind":"Gdef"},"setup_modules":{".class":"SymbolTableNode","kind":"Gdef","node":{".class":"FuncDef","abstract_status":0,"arg_kinds":[],"arg_names":[],"dataclass_transform_spec":null,"flags":[],"fullname":"modules.chart_feedback.chart_feedback_modules.setup_modules","name":"setup_modules","type":null}}},"path":"modules/chart_feedback/chart_feedback_modules.py"}